{
  "indexes": [
    {
      "collectionGroup": "publicListings",
      "queryScope": "COLLECTION",
      "fields": [
        {
          "fieldPath": "isActive",
          "order": "ASCENDING"
        },
        {
          "fieldPath": "publishedAt",
          "order": "DESCENDING"
        }
      ]
    },
    {
      "collectionGroup": "publicListings",
      "queryScope": "COLLECTION",
      "fields": [
        {
          "fieldPath": "isActive",
          "order": "ASCENDING"
        },
        {
          "fieldPath": "city",
          "order": "ASCENDING"
        },
        {
          "fieldPath": "publishedAt",
          "order": "DESCENDING"
        }
      ]
    },
    {
      "collectionGroup": "publicListings",
      "queryScope": "COLLECTION",
      "fields": [
        {
          "fieldPath": "featuredRequest",
          "order": "ASCENDING"
        },
        {
          "fieldPath": "updatedAt",
          "order": "DESCENDING"
        }
      ]
    },
    {
      "collectionGroup": "publicListings",
      "queryScope": "COLLECTION",
      "fields": [
        {
          "fieldPath": "propertyId",
          "order": "ASCENDING"
        },
        {
          "fieldPath": "isActive",
          "order": "ASCENDING"
        }
      ]
    },
    {
      "collectionGroup": "listingContactRequests",
      "queryScope": "COLLECTION",
      "fields": [
        {
          "fieldPath": "organizationId",
          "order": "ASCENDING"
        },
        {
          "fieldPath": "createdAt",
          "order": "DESCENDING"
        }
      ]
    },
    {
      "collectionGroup": "badges",
      "queryScope": "COLLECTION",
      "fields": [
        {
          "fieldPath": "targetType",
          "order": "ASCENDING"
        },
        {
          "fieldPath": "targetId",
          "order": "ASCENDING"
        },
        {
          "fieldPath": "isActive",
          "order": "ASCENDING"
        }
      ]
    },
    {
      "collectionGroup": "publicListings",
      "queryScope": "COLLECTION",
      "fields": [
        {
          "fieldPath": "organizationId",
          "order": "ASCENDING"
        },
        {
          "fieldPath": "isActive",
          "order": "ASCENDING"
        },
        {
          "fieldPath": "publishedAt",
          "order": "DESCENDING"
        }
      ]
    },
    {
      "collectionGroup": "marketplaceRubriques",
      "queryScope": "COLLECTION",
      "fields": [
        {
          "fieldPath": "active",
          "order": "ASCENDING"
        },
        {
          "fieldPath": "ordre",
          "order": "ASCENDING"
        }
      ]
    },
    {
      "collectionGroup": "marketplaceArticles",
      "queryScope": "COLLECTION",
      "fields": [
        {
          "fieldPath": "rubriqueId",
          "order": "ASCENDING"
        },
        {
          "fieldPath": "active",
          "order": "ASCENDING"
        },
        {
          "fieldPath": "ordre",
          "order": "ASCENDING"
        }
      ]
    },
    {
      "collectionGroup": "marketplaceArticles",
      "queryScope": "COLLECTION",
      "fields": [
        {
          "fieldPath": "slug",
          "order": "ASCENDING"
        },
        {
          "fieldPath": "active",
          "order": "ASCENDING"
        }
      ]
    }
  ],
  "fieldOverrides": []
}